LICENSE.md
MANIFEST.in
README.md
setup.py
buycoins_client/__init__.py
buycoins_client.egg-info/PKG-INFO
buycoins_client.egg-info/SOURCES.txt
buycoins_client.egg-info/dependency_links.txt
buycoins_client.egg-info/requires.txt
buycoins_client.egg-info/top_level.txt
buycoins_client.egg-info/zip-safe
buycoins_client/components/__init__.py
buycoins_client/components/accounts.py
buycoins_client/components/auth.py
buycoins_client/components/balances.py
buycoins_client/components/orders.py
buycoins_client/components/prices.py
buycoins_client/components/transfers.py
buycoins_client/components/utilities.py
tests/__init__.py
tests/test_accounts.py
tests/test_auth.py
tests/test_balances.py
tests/test_orders.py
tests/test_prices.py
tests/test_transfers.py