Metadata-Version: 2.1
Name: buycoins-client
Version: 1.4
Summary: Buycoins API Python client
Home-page: https://github.com/ChukwuEmekaAjah/buycoins_python
Author: Chukwuemeka Ajah
Author-email: talk2ajah@gmail.com
License: MIT
Platform: UNKNOWN
